scolp.py
scolp-0.1.5.dist-info/LICENSE
scolp-0.1.5.dist-info/METADATA
scolp-0.1.5.dist-info/WHEEL
scolp-0.1.5.dist-info/top_level.txt
scolp-0.1.5.dist-info/RECORD
