Metadata-Version: 2.1
Name: scolp
Version: 0.1.5
Summary: Streaming Column Printer
Home-page: https://github.com/davidohana/python-scolp
Author: David Ohana
Author-email: davidoha@gmail.com
License: UNKNOWN
Platform: UNKNOWN
Classifier: Programming Language :: Python :: 3.6
Classifier: Programming Language :: Python :: 3.7
Classifier: License :: OSI Approved :: MIT License
Classifier: Operating System :: OS Independent
Classifier: Topic :: Software Development :: Libraries
